py_stac-0.2.6.dist-info/METADATA
py_stac-0.2.6.dist-info/RECORD
py_stac-0.2.6.dist-info/WHEEL
py_stac-0.2.6.dist-info/entry_points.txt
py_stac-0.2.6.dist-info/top_level.txt
stac/__init__.py
stac/cli.py
stac/stac.py
stac/models/__init__.py
stac/models/asset.py
stac/models/base.py
stac/models/collection.py
stac/models/geojson_type.py
stac/models/item.py
stac/models/link.py
stac/models/properties.py
stac/models/extensions/__init__.py
stac/models/extensions/band.py
stac/models/extensions/product.py
tests/__init__.py
tests/test_stac.py
