Metadata-Version: 2.1
Name: py-stac
Version: 0.2.6
Summary: Python command line and library utilities for interactingwith and creating STAC compliant files.
Home-page: https://github.com/geobeyond/py-stac
Author: Geobeyond
Author-email: info@geobeyond.it
License: Apache Software License 2.0
Keywords: pystac,py-stac,imagery,raster,catalog,STAC
Platform: UNKNOWN
Classifier: Development Status :: 2 - Pre-Alpha
Classifier: Intended Audience :: Developers
Classifier: License :: OSI Approved :: Apache Software License
Classifier: Natural Language :: English
Classifier: Programming Language :: Python :: 2.7
Classifier: Programming Language :: Python :: 3
Classifier: Programming Language :: Python :: 3.4
Classifier: Programming Language :: Python :: 3.5
Classifier: Programming Language :: Python :: 3.6
Requires-Dist: python-dateutil (==2.6.1)
Requires-Dist: rasterio (==1.0a12)
Requires-Dist: Click (>=6.0)
Requires-Dist: geojson (==2.3.0)
Requires-Dist: requests (>=2.18.0)
Requires-Dist: marshmallow (>=3.0.0b12)
Requires-Dist: typing (==3.6.2); python_version <= "3.6"
